bacchus/__init__.py
bacchus/base.py
bacchus/certificates.py
bacchus/cli.py
bacchus/compose.py
bacchus/jackett.py
bacchus/jellyfin.py
bacchus/kodi.py
bacchus/lazylibrarian.py
bacchus/lidarr.py
bacchus/medusa.py
bacchus/nextcloud.py
bacchus/nginx.py
bacchus/openvpn.py
bacchus/pihole.py
bacchus/radarr.py
bacchus/templates/docker-compose.yml
bacchus/templates/jackett/Indexers/1337x.json
bacchus/templates/jackett/Indexers/1337x.json.bak
bacchus/templates/jackett/Indexers/anidex.json
bacchus/templates/jackett/Indexers/ettv.json
bacchus/templates/jackett/Indexers/kickasstorrent.json
bacchus/templates/jackett/Indexers/kickasstorrent.json.bak
bacchus/templates/jackett/Indexers/magnetdl.json
bacchus/templates/jackett/Indexers/magnetdl.json.bak
bacchus/templates/jackett/Indexers/nyaasi.json
bacchus/templates/jackett/Indexers/skytorrentsclone.json
bacchus/templates/jackett/Indexers/skytorrentsclone.json.bak
bacchus/templates/jackett/Indexers/thepiratebay.json
bacchus/templates/jackett/Indexers/thepiratebay.json.bak
bacchus/templates/nginx.tpl
bacchus/transmission.py
bacchus-1.1.0.dist-info/entry_points.txt
bacchus-1.1.0.dist-info/WHEEL
bacchus-1.1.0.dist-info/METADATA
bacchus-1.1.0.dist-info/RECORD
